xxb/__init__.py
xxb/elegant/__init__.py
xxb/elegant/girl/__init__.py
xxb/elegant/girl/information.py
xxb/elegant/girl/message.py
dwy-0.1.dist-info/METADATA
dwy-0.1.dist-info/WHEEL
dwy-0.1.dist-info/top_level.txt
dwy-0.1.dist-info/RECORD
