Metadata-Version: 2.1
Name: dwy
Version: 0.1
Summary: 邓文怡
Author: dwy
License: UNKNOWN
Platform: UNKNOWN
